pisync/__about__.py
pisync/__init__.py
pisync/config/__init__.py
pisync/config/base_config.py
pisync/config/local_config.py
pisync/config/remote_config.py
pisync/util/__init__.py
pisync-0.0.9.dist-info/METADATA
pisync-0.0.9.dist-info/WHEEL
pisync-0.0.9.dist-info/licenses/LICENSE
pisync-0.0.9.dist-info/RECORD
