Metadata-Version: 2.1
Name: pisync
Version: 0.0.9
Summary: Minimal incremental backup script using rsync 
Project-URL: Documentation, https://github.com/erietz/pisync#readme
Project-URL: Issues, https://github.com/erietz/pisync/issues
Project-URL: Source, https://github.com/erietz/pisync
Author-email: erietz <ewrietz@gmail.com>
License-Expression: GPL-3.0-or-later
License-File: LICENSE
Classifier: Development Status :: 4 - Beta
Classifier: Programming Language :: Python
Classifier: Programming Language :: Python :: 3.7
Classifier: Programming Language :: Python :: 3.8
Classifier: Programming Language :: Python :: 3.9
Classifier: Programming Language :: Python :: 3.10
Classifier: Programming Language :: Python :: 3.11
Classifier: Programming Language :: Python :: Implementation :: CPython
Classifier: Programming Language :: Python :: Implementation :: PyPy
Requires-Python: >=3.7
Requires-Dist: fabric
